get_filename/__init__.py
get_filename/get_filename.py
get_filename-1.0.0.dist-info/LICENSE
get_filename-1.0.0.dist-info/METADATA
get_filename-1.0.0.dist-info/WHEEL
get_filename-1.0.0.dist-info/top_level.txt
get_filename-1.0.0.dist-info/RECORD
