Metadata-Version: 2.1
Name: get-filename
Version: 1.0.0
Summary: from a filename(str) extension or name
Home-page: https://github.com/we684123/get_filename
Author: we684123
Author-email: we684123@gmail.com
License: MIT
Keywords: filename,extension
Platform: any
